<?xml version="1.0" encoding="utf-8"?>
<LanguageData>
  <Firebeater.label>Batteur de feu</Firebeater.label>
  <Firebeater.description>Un baton avec un rabat en cuir plat utilisé pour combattre les incendies.</Firebeater.description>
  <Firebeater.tools.0.label>manche</Firebeater.tools.0.label>
  <Firebeater.tools.1.label>extrémité</Firebeater.tools.1.label>
  <!--The following translations were generated by https://www.deepl.com/-->
  <!-- EN: Firebeater -->
  <!-- EN: A polearm with a flat leather flap used for beating down fires. -->
  <!-- EN: shaft -->
  <Firebeater.tools.shaft.label>arbre</Firebeater.tools.shaft.label>
  <!-- EN: point -->
  <Firebeater.tools.point.label>point</Firebeater.tools.point.label>
</LanguageData>
